django_ca/__init__.py
django_ca/admin.py
django_ca/apps.py
django_ca/checks.py
django_ca/conf.py
django_ca/constants.py
django_ca/converters.py
django_ca/deprecation.py
django_ca/fields.py
django_ca/forms.py
django_ca/managers.py
django_ca/migration_helpers.py
django_ca/modelfields.py
django_ca/models.py
django_ca/mypy.py
django_ca/profiles.py
django_ca/py.typed
django_ca/querysets.py
django_ca/signals.py
django_ca/tasks.py
django_ca/typehints.py
django_ca/urls.py
django_ca/utils.py
django_ca/views.py
django_ca/widgets.py
django_ca/acme/__init__.py
django_ca/acme/constants.py
django_ca/acme/errors.py
django_ca/acme/messages.py
django_ca/acme/responses.py
django_ca/acme/utils.py
django_ca/acme/validation.py
django_ca/acme/views.py
django_ca/api/__init__.py
django_ca/api/auth.py
django_ca/api/endpoints.py
django_ca/api/errors.py
django_ca/api/schemas.py
django_ca/api/utils.py
django_ca/extensions/__init__.py
django_ca/extensions/text.py
django_ca/extensions/utils.py
django_ca/key_backends/__init__.py
django_ca/key_backends/base.py
django_ca/key_backends/db/__init__.py
django_ca/key_backends/db/backend.py
django_ca/key_backends/db/models.py
django_ca/key_backends/db/ocsp_backend.py
django_ca/key_backends/hsm/__init__.py
django_ca/key_backends/hsm/backend.py
django_ca/key_backends/hsm/keys.py
django_ca/key_backends/hsm/mixins.py
django_ca/key_backends/hsm/models.py
django_ca/key_backends/hsm/ocsp_backend.py
django_ca/key_backends/hsm/session.py
django_ca/key_backends/hsm/typehints.py
django_ca/key_backends/hsm/utils.py
django_ca/key_backends/storages/__init__.py
django_ca/key_backends/storages/backend.py
django_ca/key_backends/storages/models.py
django_ca/key_backends/storages/ocsp_backend.py
django_ca/management/__init__.py
django_ca/management/actions.py
django_ca/management/base.py
django_ca/management/mixins.py
django_ca/management/commands/__init__.py
django_ca/management/commands/cache_crls.py
django_ca/management/commands/cert_watchers.py
django_ca-2.5.0.dist-info/licenses/LICENSE
django_ca-2.5.0.dist-info/METADATA
django_ca-2.5.0.dist-info/WHEEL
django_ca-2.5.0.dist-info/top_level.txt
django_ca-2.5.0.dist-info/RECORD
