Metadata-Version: 2.4
Name: django-ca
Version: 2.5.0
Summary: A Django app providing a TLS certificate authority.
Author-email: Mathias Ertl <mati@er.tl>
License-Expression: GPL-3.0-or-later
Project-URL: Homepage, https://github.com/mathiasertl/django-ca/
Project-URL: Documentation, https://django-ca.readthedocs.io/
Project-URL: Source, https://github.com/mathiasertl/django-ca/
Project-URL: Issues, https://github.com/mathiasertl/django-ca/issues
Project-URL: Changelog, https://django-ca.readthedocs.io/en/latest/changelog.html
Classifier: Development Status :: 5 - Production/Stable
Classifier: Framework :: Django :: 5.2
Classifier: Framework :: Django :: 6.0
Classifier: Framework :: Django
Classifier: Intended Audience :: Developers
Classifier: Intended Audience :: System Administrators
Classifier: Programming Language :: Python :: 3
Classifier: Programming Language :: Python :: 3.10
Classifier: Programming Language :: Python :: 3.11
Classifier: Programming Language :: Python :: 3.12
Classifier: Programming Language :: Python :: 3.13
Classifier: Programming Language :: Python :: 3.14
Classifier: Programming Language :: Python :: 3 :: Only
Classifier: Topic :: Security :: Cryptography
Classifier: Topic :: Security
Classifier: Typing :: Typed
Requires-Python: >=3.10
License-File: LICENSE
Requires-Dist: Django~=5.2.0; python_version < "3.12"
Requires-Dist: Django>=5.2; python_version >= "3.12"
Requires-Dist: acme>=5.0
Requires-Dist: asn1crypto>=1.5
Requires-Dist: cryptography>=45
Requires-Dist: django-object-actions>=5.0
Requires-Dist: dnspython>=2.7
Requires-Dist: idna>=3.10
Requires-Dist: josepy>=2.1.0
Requires-Dist: packaging
Requires-Dist: pydantic>=2.11
Requires-Dist: requests>=2.32.3
Requires-Dist: typing_extensions>=4.6.0; python_version < "3.12"
Provides-Extra: api
Requires-Dist: django-ninja>=1.5.1; extra == "api"
Provides-Extra: celery
Requires-Dist: celery>=5.5; extra == "celery"
Provides-Extra: hsm
Requires-Dist: python-pkcs11>=0.9; extra == "hsm"
Provides-Extra: mysql
Requires-Dist: mysqlclient; extra == "mysql"
Provides-Extra: postgres
Requires-Dist: psycopg[c,pool]>=3.1; extra == "postgres"
Provides-Extra: redis
Requires-Dist: hiredis>=3.1.0; extra == "redis"
Requires-Dist: redis>=6.0; extra == "redis"
Provides-Extra: yaml
Requires-Dist: PyYAML>=6.0.0; extra == "yaml"
Dynamic: license-file
